condat_gridconv/shift.cpython-310-x86_64-linux-gnu.so
condat_gridconv/gridconv.py
condat_gridconv/__init__.py
condat_gridconv-0.2.1.dist-info/WHEEL
condat_gridconv-0.2.1.dist-info/RECORD
condat_gridconv-0.2.1.dist-info/METADATA
