Metadata-Version: 2.1
Name: condat-gridconv
Version: 0.2.1
Summary: Convert data from hexagonal pixels to cartesian grid
Author-Email: European XFEL GmbH <da-support@xfel.eu>
Project-URL: Source, https://github.com/European-XFEL/condat-gridconv
Requires-Python: >=3.8
Requires-Dist: numpy
